jupiter_python_sdk/__init__.py
jupiter_python_sdk/jupiter.py
jupiter_python_sdk-0.0.2.0.dist-info/LICENSE.txt
jupiter_python_sdk-0.0.2.0.dist-info/METADATA
jupiter_python_sdk-0.0.2.0.dist-info/WHEEL
jupiter_python_sdk-0.0.2.0.dist-info/top_level.txt
jupiter_python_sdk-0.0.2.0.dist-info/RECORD
