Metadata-Version: 2.1
Name: jupiter-python-sdk
Version: 0.0.2.0
Summary: Jupiter Python SDK
Author: TaoDev
Author-email: taodev3@proton.me
License: LICENSE.txt
Keywords: python,solana,jupiter,dex,trading,sdk
Classifier: Development Status :: 3 - Alpha
Classifier: Intended Audience :: Developers
Classifier: Programming Language :: Python :: 3
Classifier: Operating System :: Unix
Classifier: Operating System :: MacOS :: MacOS X
Classifier: Operating System :: Microsoft :: Windows
License-File: LICENSE.txt
